LICENSE
MANIFEST.in
README.md
setup.py
smelli/__init__.py
smelli/_version.py
smelli/ckm.py
smelli/classes.py
smelli/test_ckm.py
smelli/test_classes.py
smelli/test_package.py
smelli/util.py
smelli.egg-info/PKG-INFO
smelli.egg-info/SOURCES.txt
smelli.egg-info/dependency_links.txt
smelli.egg-info/requires.txt
smelli.egg-info/top_level.txt
smelli/data/cache/fast_likelihood_leptons.yaml_CKMSchemeRmuBtaunuBxlnuDeltaM.p
smelli/data/cache/fast_likelihood_leptons.yaml_fix_ckm.p
smelli/data/cache/fast_likelihood_quarks.yaml_CKMSchemeRmuBtaunuBxlnuDeltaM.p
smelli/data/cache/fast_likelihood_quarks_fixckm.yaml_fix_ckm.p
smelli/data/test/wcxf.yaml
smelli/data/yaml/fast_likelihood_leptons.yaml
smelli/data/yaml/fast_likelihood_quarks.yaml
smelli/data/yaml/fast_likelihood_quarks_fixckm.yaml
smelli/data/yaml/likelihood_bcpv.yaml
smelli/data/yaml/likelihood_bqnunu.yaml
smelli/data/yaml/likelihood_eeww.yaml
smelli/data/yaml/likelihood_ewpt.yaml
smelli/data/yaml/likelihood_higgs.yaml
smelli/data/yaml/likelihood_lept.yaml
smelli/data/yaml/likelihood_lfu_fccc.yaml
smelli/data/yaml/likelihood_lfu_fcnc.yaml
smelli/data/yaml/likelihood_lfv.yaml
smelli/data/yaml/likelihood_rd_rds.yaml
smelli/data/yaml/likelihood_zlfv.yaml
smelli/data/yaml/measurements_bcpv.yaml
smelli/data/yaml/measurements_bqnunu.yaml
smelli/data/yaml/measurements_eeww.yaml
smelli/data/yaml/measurements_ewpt.yaml
smelli/data/yaml/measurements_fixckm.yaml
smelli/data/yaml/measurements_higgs.yaml
smelli/data/yaml/measurements_lept.yaml
smelli/data/yaml/measurements_leptons.yaml
smelli/data/yaml/measurements_lfu_fccc.yaml
smelli/data/yaml/measurements_lfu_fcnc.yaml
smelli/data/yaml/measurements_lfv.yaml
smelli/data/yaml/measurements_quarks.yaml
smelli/data/yaml/measurements_rd_rds.yaml
smelli/data/yaml/measurements_zlfv.yaml
smelli/data/yaml/observables_bctaunu_diff.yaml
smelli/data/yaml/observables_bctaunu_other.yaml
smelli/data/yaml/observables_bdll.yaml
smelli/data/yaml/observables_beta.yaml
smelli/data/yaml/observables_bkstaree_lhcb.yaml
smelli/data/yaml/observables_bkstarll_lfu.yaml
smelli/data/yaml/observables_bkstarmumu_atlas_p.yaml
