Metadata-Version: 2.1
Name: smelli
Version: 2.4.1
Summary: A Python package providing a global likelihood function in the space of dimension-6 Wilson coefficients of the Standard Model Effective Field Theory (SMEFT)
Home-page: UNKNOWN
Author: Jason Aebischer <jason.aebischer@tum.de>, Jacky Kumar <jacky.kumar@umontreal.ca>, Peter Stangl <peter.stangl@lapth.cnrs.fr>, David M. Straub <david.straub@tum.de>
License: MIT
Platform: UNKNOWN
Provides-Extra: testing
License-File: LICENSE
